bfabric_app_runner/__init__.py
bfabric_app_runner/py.typed
bfabric_app_runner/actions/__init__.py
bfabric_app_runner/actions/config_file.py
bfabric_app_runner/actions/execute.py
bfabric_app_runner/actions/types.py
bfabric_app_runner/app_runner/__init__.py
bfabric_app_runner/app_runner/resolve_app.py
bfabric_app_runner/app_runner/runner.py
bfabric_app_runner/bfabric_integration/__init__.py
bfabric_app_runner/bfabric_integration/slurm.py
bfabric_app_runner/bfabric_integration/submitter/__init__.py
bfabric_app_runner/bfabric_integration/submitter/slurm_job_template.bash.mako
bfabric_app_runner/bfabric_integration/submitter/slurm_job_template.py
bfabric_app_runner/bfabric_integration/submitter/config/__init__.py
bfabric_app_runner/bfabric_integration/submitter/config/slurm_params.py
bfabric_app_runner/bfabric_integration/submitter/config/slurm_workunit_params.py
bfabric_app_runner/bfabric_integration/wrapper/__init__.py
bfabric_app_runner/bfabric_integration/wrapper/wrap_app_yaml_template.bash.mako
bfabric_app_runner/bfabric_integration/wrapper/wrap_app_yaml_template.py
bfabric_app_runner/cli/__init__.py
bfabric_app_runner/cli/__main__.py
bfabric_app_runner/cli/cmd_action.py
bfabric_app_runner/cli/cmd_prepare.py
bfabric_app_runner/cli/cmd_run.py
bfabric_app_runner/cli/inputs.py
bfabric_app_runner/cli/outputs.py
bfabric_app_runner/cli/validate.py
bfabric_app_runner/commands/__init__.py
bfabric_app_runner/commands/command_docker.py
bfabric_app_runner/commands/command_exec.py
bfabric_app_runner/commands/command_python_env.py
bfabric_app_runner/commands/command_shell.py
bfabric_app_runner/commands/execute.py
bfabric_app_runner/deploy/__init__.py
bfabric_app_runner/dispatch/__init__.py
bfabric_app_runner/dispatch/dispatch_individual_resources.py
bfabric_app_runner/dispatch/dispatch_resource_flow.py
bfabric_app_runner/dispatch/dispatch_single_dataset_flow.py
bfabric_app_runner/dispatch/dispatch_single_resource_flow.py
bfabric_app_runner/dispatch/generic.py
bfabric_app_runner-0.5.0.dist-info/METADATA
bfabric_app_runner-0.5.0.dist-info/WHEEL
bfabric_app_runner-0.5.0.dist-info/entry_points.txt
bfabric_app_runner-0.5.0.dist-info/RECORD
